syntactic_metaphor/__init__.py
syntactic_metaphor-0.3.5.dist-info/METADATA
syntactic_metaphor-0.3.5.dist-info/WHEEL
syntactic_metaphor-0.3.5.dist-info/top_level.txt
syntactic_metaphor-0.3.5.dist-info/RECORD
