Metadata-Version: 2.1
Name: syntactic-metaphor
Version: 0.3.5
Summary: Educational phrase-structure metaphor for structured control flow: supplementary materials
Home-page: https://katego.lt/metaphor
Author: Ignas Rudaitis
Author-email: ignas.rudaitis@gmail.com
License: MIT
Platform: UNKNOWN
